cudatools/__init__.py
cudatools-0.0.1.dist-info/METADATA
cudatools-0.0.1.dist-info/WHEEL
cudatools-0.0.1.dist-info/top_level.txt
cudatools-0.0.1.dist-info/RECORD
