Metadata-Version: 1.0
Name: cudatools
Version: 0.0.1
Summary: CUDA utils accessible via python
Home-page: http://github.com/krzysg/cudautils
Author: Krzysztof Gonciarz
Author-email: krzysztof.gonciarz@gmail.com
License: MIT
Platform: UNKNOWN
